{
  "cascadeEnabled" : false,
  "dataLockingOptions" : {
    "versionColumnName" : "VERSION",
    "lockingStrategy" : "NONE"
  },
  "description" : null,
  "draft" : false,
  "name" : "StudentPortal_DB",
  "packageName" : "com.student_usecase.studentportal_db",
  "tables" : [ {
    "catalog" : "StudentPortal_DB",
    "columns" : [ {
      "columnValue" : {
        "insertable" : true,
        "updatable" : true,
        "defaultValue" : null,
        "type" : "user-defined"
      },
      "constraintList" : null,
      "fieldName" : "academicYear",
      "foreignKey" : false,
      "generatorType" : "assigned",
      "generatorValue" : null,
      "hidden" : false,
      "javaType" : "date",
      "length" : 0,
      "name" : "ACADEMIC_YEAR",
      "nullable" : false,
      "oldName" : "ACADEMIC_YEAR",
      "partOfAnyRelation" : false,
      "partOfForeignKey" : false,
      "partOfPrimaryKey" : true,
      "partOfUniqueKey" : false,
      "period" : false,
      "precision" : 0,
      "primaryKey" : false,
      "scale" : 0,
      "sequenceSchema" : null,
      "sqlType" : "date",
      "unique" : false
    }, {
      "columnValue" : {
        "insertable" : true,
        "updatable" : true,
        "defaultValue" : null,
        "type" : "user-defined"
      },
      "constraintList" : null,
      "fieldName" : "classroom",
      "foreignKey" : false,
      "generatorType" : "assigned",
      "generatorValue" : null,
      "hidden" : false,
      "javaType" : "string",
      "length" : 255,
      "name" : "CLASSROOM",
      "nullable" : false,
      "oldName" : "CLASSROOM",
      "partOfAnyRelation" : false,
      "partOfForeignKey" : false,
      "partOfPrimaryKey" : true,
      "partOfUniqueKey" : false,
      "period" : false,
      "precision" : 0,
      "primaryKey" : false,
      "scale" : 0,
      "sequenceSchema" : null,
      "sqlType" : "string",
      "unique" : false
    }, {
      "columnValue" : {
        "insertable" : true,
        "updatable" : true,
        "defaultValue" : null,
        "type" : "user-defined"
      },
      "constraintList" : null,
      "fieldName" : "classteacher",
      "foreignKey" : false,
      "generatorType" : "assigned",
      "generatorValue" : null,
      "hidden" : false,
      "javaType" : "string",
      "length" : 255,
      "name" : "CLASSTEACHER",
      "nullable" : false,
      "oldName" : "CLASSTEACHER",
      "partOfAnyRelation" : false,
      "partOfForeignKey" : false,
      "partOfPrimaryKey" : true,
      "partOfUniqueKey" : false,
      "period" : false,
      "precision" : 0,
      "primaryKey" : false,
      "scale" : 0,
      "sequenceSchema" : null,
      "sqlType" : "string",
      "unique" : false
    }, {
      "columnValue" : {
        "insertable" : true,
        "updatable" : true,
        "defaultValue" : null,
        "type" : "user-defined"
      },
      "constraintList" : null,
      "fieldName" : "standard",
      "foreignKey" : false,
      "generatorType" : "assigned",
      "generatorValue" : null,
      "hidden" : false,
      "javaType" : "string",
      "length" : 255,
      "name" : "STANDARD",
      "nullable" : false,
      "oldName" : "STANDARD",
      "partOfAnyRelation" : false,
      "partOfForeignKey" : false,
      "partOfPrimaryKey" : true,
      "partOfUniqueKey" : false,
      "period" : false,
      "precision" : 0,
      "primaryKey" : false,
      "scale" : 0,
      "sequenceSchema" : null,
      "sqlType" : "string",
      "unique" : false
    } ],
    "constraints" : [ ],
    "entityName" : "Academics",
    "filter" : null,
    "fullyQualifiedName" : "com.student_usecase.studentportal_db.Academics",
    "ignoreRefreshAfterInsert" : false,
    "name" : "ACADEMICS",
    "oldName" : "ACADEMICS",
    "primaryKey" : {
      "columns" : [ "ACADEMIC_YEAR", "CLASSROOM", "CLASSTEACHER", "STANDARD" ],
      "composite" : true,
      "generator" : {
        "generatorType" : "assigned",
        "generatorValue" : null,
        "schemaName" : null
      },
      "name" : "PRIMARY",
      "virtual" : false
    },
    "relations" : [ ],
    "schema" : null,
    "tableDataLockingOptions" : {
      "versionColumnName" : "VERSION",
      "lockingStrategy" : "NONE",
      "overrideStrategy" : "INHERIT"
    },
    "temporals" : [ ],
    "type" : "TABLE"
  }, {
    "catalog" : "StudentPortal_DB",
    "columns" : [ {
      "columnValue" : {
        "insertable" : true,
        "updatable" : true,
        "defaultValue" : null,
        "type" : "user-defined"
      },
      "constraintList" : null,
      "fieldName" : "academicYear",
      "foreignKey" : false,
      "generatorType" : "assigned",
      "generatorValue" : null,
      "hidden" : false,
      "javaType" : "date",
      "length" : 0,
      "name" : "ACADEMIC_YEAR",
      "nullable" : false,
      "oldName" : "ACADEMIC_YEAR",
      "partOfAnyRelation" : false,
      "partOfForeignKey" : false,
      "partOfPrimaryKey" : true,
      "partOfUniqueKey" : false,
      "period" : false,
      "precision" : 0,
      "primaryKey" : false,
      "scale" : 0,
      "sequenceSchema" : null,
      "sqlType" : "date",
      "unique" : false
    }, {
      "columnValue" : {
        "insertable" : true,
        "updatable" : true,
        "defaultValue" : null,
        "type" : "user-defined"
      },
      "constraintList" : null,
      "fieldName" : "standard",
      "foreignKey" : false,
      "generatorType" : "assigned",
      "generatorValue" : null,
      "hidden" : false,
      "javaType" : "string",
      "length" : 255,
      "name" : "STANDARD",
      "nullable" : false,
      "oldName" : "STANDARD",
      "partOfAnyRelation" : false,
      "partOfForeignKey" : false,
      "partOfPrimaryKey" : true,
      "partOfUniqueKey" : false,
      "period" : false,
      "precision" : 0,
      "primaryKey" : false,
      "scale" : 0,
      "sequenceSchema" : null,
      "sqlType" : "string",
      "unique" : false
    }, {
      "columnValue" : {
        "insertable" : true,
        "updatable" : true,
        "defaultValue" : null,
        "type" : "user-defined"
      },
      "constraintList" : null,
      "fieldName" : "subjectName",
      "foreignKey" : false,
      "generatorType" : "assigned",
      "generatorValue" : null,
      "hidden" : false,
      "javaType" : "string",
      "length" : 255,
      "name" : "SUBJECT_NAME",
      "nullable" : false,
      "oldName" : "SUBJECT_NAME",
      "partOfAnyRelation" : false,
      "partOfForeignKey" : false,
      "partOfPrimaryKey" : true,
      "partOfUniqueKey" : false,
      "period" : false,
      "precision" : 0,
      "primaryKey" : false,
      "scale" : 0,
      "sequenceSchema" : null,
      "sqlType" : "string",
      "unique" : false
    }, {
      "columnValue" : {
        "insertable" : true,
        "updatable" : true,
        "defaultValue" : null,
        "type" : "user-defined"
      },
      "constraintList" : null,
      "fieldName" : "subjectTeacher",
      "foreignKey" : false,
      "generatorType" : "assigned",
      "generatorValue" : null,
      "hidden" : false,
      "javaType" : "string",
      "length" : 255,
      "name" : "SUBJECT_TEACHER",
      "nullable" : false,
      "oldName" : "SUBJECT_TEACHER",
      "partOfAnyRelation" : false,
      "partOfForeignKey" : false,
      "partOfPrimaryKey" : true,
      "partOfUniqueKey" : false,
      "period" : false,
      "precision" : 0,
      "primaryKey" : false,
      "scale" : 0,
      "sequenceSchema" : null,
      "sqlType" : "string",
      "unique" : false
    } ],
    "constraints" : [ ],
    "entityName" : "AcademicSubjects",
    "filter" : null,
    "fullyQualifiedName" : "com.student_usecase.studentportal_db.AcademicSubjects",
    "ignoreRefreshAfterInsert" : false,
    "name" : "ACADEMIC_SUBJECTS",
    "oldName" : "ACADEMIC_SUBJECTS",
    "primaryKey" : {
      "columns" : [ "ACADEMIC_YEAR", "STANDARD", "SUBJECT_NAME", "SUBJECT_TEACHER" ],
      "composite" : true,
      "generator" : {
        "generatorType" : "assigned",
        "generatorValue" : null,
        "schemaName" : null
      },
      "name" : "PRIMARY",
      "virtual" : false
    },
    "relations" : [ ],
    "schema" : null,
    "tableDataLockingOptions" : {
      "versionColumnName" : "VERSION",
      "lockingStrategy" : "NONE",
      "overrideStrategy" : "INHERIT"
    },
    "temporals" : [ ],
    "type" : "TABLE"
  }, {
    "catalog" : "StudentPortal_DB",
    "columns" : [ {
      "columnValue" : {
        "insertable" : true,
        "updatable" : true,
        "defaultValue" : null,
        "type" : "user-defined"
      },
      "constraintList" : null,
      "fieldName" : "academicYear",
      "foreignKey" : false,
      "generatorType" : "assigned",
      "generatorValue" : null,
      "hidden" : false,
      "javaType" : "date",
      "length" : 0,
      "name" : "ACADEMIC_YEAR",
      "nullable" : false,
      "oldName" : "ACADEMIC_YEAR",
      "partOfAnyRelation" : false,
      "partOfForeignKey" : false,
      "partOfPrimaryKey" : true,
      "partOfUniqueKey" : false,
      "period" : false,
      "precision" : 0,
      "primaryKey" : false,
      "scale" : 0,
      "sequenceSchema" : null,
      "sqlType" : "date",
      "unique" : false
    }, {
      "columnValue" : {
        "insertable" : true,
        "updatable" : true,
        "defaultValue" : null,
        "type" : "user-defined"
      },
      "constraintList" : null,
      "fieldName" : "grade",
      "foreignKey" : false,
      "generatorType" : "assigned",
      "generatorValue" : null,
      "hidden" : false,
      "javaType" : "string",
      "length" : 255,
      "name" : "GRADE",
      "nullable" : false,
      "oldName" : "GRADE",
      "partOfAnyRelation" : false,
      "partOfForeignKey" : false,
      "partOfPrimaryKey" : true,
      "partOfUniqueKey" : false,
      "period" : false,
      "precision" : 0,
      "primaryKey" : false,
      "scale" : 0,
      "sequenceSchema" : null,
      "sqlType" : "string",
      "unique" : false
    }, {
      "columnValue" : {
        "insertable" : true,
        "updatable" : true,
        "defaultValue" : null,
        "type" : "user-defined"
      },
      "constraintList" : null,
      "fieldName" : "marks",
      "foreignKey" : false,
      "generatorType" : "assigned",
      "generatorValue" : null,
      "hidden" : false,
      "javaType" : "short",
      "length" : 0,
      "name" : "MARKS",
      "nullable" : false,
      "oldName" : "MARKS",
      "partOfAnyRelation" : false,
      "partOfForeignKey" : false,
      "partOfPrimaryKey" : true,
      "partOfUniqueKey" : false,
      "period" : false,
      "precision" : 5,
      "primaryKey" : false,
      "scale" : 0,
      "sequenceSchema" : null,
      "sqlType" : "number",
      "unique" : false
    }, {
      "columnValue" : {
        "insertable" : true,
        "updatable" : true,
        "defaultValue" : null,
        "type" : "user-defined"
      },
      "constraintList" : null,
      "fieldName" : "rollnumber",
      "foreignKey" : false,
      "generatorType" : "assigned",
      "generatorValue" : null,
      "hidden" : false,
      "javaType" : "integer",
      "length" : 0,
      "name" : "ROLLNUMBER",
      "nullable" : false,
      "oldName" : "ROLLNUMBER",
      "partOfAnyRelation" : false,
      "partOfForeignKey" : false,
      "partOfPrimaryKey" : true,
      "partOfUniqueKey" : false,
      "period" : false,
      "precision" : 10,
      "primaryKey" : false,
      "scale" : 0,
      "sequenceSchema" : null,
      "sqlType" : "number",
      "unique" : false
    }, {
      "columnValue" : {
        "insertable" : true,
        "updatable" : true,
        "defaultValue" : null,
        "type" : "user-defined"
      },
      "constraintList" : null,
      "fieldName" : "standard",
      "foreignKey" : false,
      "generatorType" : "assigned",
      "generatorValue" : null,
      "hidden" : false,
      "javaType" : "string",
      "length" : 255,
      "name" : "STANDARD",
      "nullable" : false,
      "oldName" : "STANDARD",
      "partOfAnyRelation" : false,
      "partOfForeignKey" : false,
      "partOfPrimaryKey" : true,
      "partOfUniqueKey" : false,
      "period" : false,
      "precision" : 0,
      "primaryKey" : false,
      "scale" : 0,
      "sequenceSchema" : null,
      "sqlType" : "string",
      "unique" : false
    } ],
    "constraints" : [ ],
    "entityName" : "Results",
    "filter" : null,
    "fullyQualifiedName" : "com.student_usecase.studentportal_db.Results",
    "ignoreRefreshAfterInsert" : false,
    "name" : "RESULTS",
    "oldName" : "RESULTS",
    "primaryKey" : {
      "columns" : [ "ACADEMIC_YEAR", "GRADE", "MARKS", "ROLLNUMBER", "STANDARD" ],
      "composite" : true,
      "generator" : {
        "generatorType" : "assigned",
        "generatorValue" : null,
        "schemaName" : null
      },
      "name" : "PRIMARY",
      "virtual" : false
    },
    "relations" : [ ],
    "schema" : null,
    "tableDataLockingOptions" : {
      "versionColumnName" : "VERSION",
      "lockingStrategy" : "NONE",
      "overrideStrategy" : "INHERIT"
    },
    "temporals" : [ ],
    "type" : "TABLE"
  }, {
    "catalog" : "StudentPortal_DB",
    "columns" : [ {
      "columnValue" : {
        "insertable" : true,
        "updatable" : true,
        "defaultValue" : null,
        "type" : "user-defined"
      },
      "constraintList" : null,
      "fieldName" : "standardId",
      "foreignKey" : false,
      "generatorType" : "assigned",
      "generatorValue" : null,
      "hidden" : false,
      "javaType" : "string",
      "length" : 255,
      "name" : "STANDARD_ID",
      "nullable" : false,
      "oldName" : "STANDARD_ID",
      "partOfAnyRelation" : false,
      "partOfForeignKey" : false,
      "partOfPrimaryKey" : true,
      "partOfUniqueKey" : false,
      "period" : false,
      "precision" : 0,
      "primaryKey" : false,
      "scale" : 0,
      "sequenceSchema" : null,
      "sqlType" : "string",
      "unique" : false
    }, {
      "columnValue" : {
        "insertable" : true,
        "updatable" : true,
        "defaultValue" : null,
        "type" : "user-defined"
      },
      "constraintList" : null,
      "fieldName" : "standardName",
      "foreignKey" : false,
      "generatorType" : "assigned",
      "generatorValue" : null,
      "hidden" : false,
      "javaType" : "string",
      "length" : 255,
      "name" : "STANDARD_NAME",
      "nullable" : false,
      "oldName" : "STANDARD_NAME",
      "partOfAnyRelation" : false,
      "partOfForeignKey" : false,
      "partOfPrimaryKey" : true,
      "partOfUniqueKey" : false,
      "period" : false,
      "precision" : 0,
      "primaryKey" : false,
      "scale" : 0,
      "sequenceSchema" : null,
      "sqlType" : "string",
      "unique" : false
    } ],
    "constraints" : [ ],
    "entityName" : "StandardDetails",
    "filter" : null,
    "fullyQualifiedName" : "com.student_usecase.studentportal_db.StandardDetails",
    "ignoreRefreshAfterInsert" : false,
    "name" : "STANDARD_DETAILS",
    "oldName" : "STANDARD_DETAILS",
    "primaryKey" : {
      "columns" : [ "STANDARD_ID", "STANDARD_NAME" ],
      "composite" : true,
      "generator" : {
        "generatorType" : "assigned",
        "generatorValue" : null,
        "schemaName" : null
      },
      "name" : "PRIMARY",
      "virtual" : false
    },
    "relations" : [ ],
    "schema" : null,
    "tableDataLockingOptions" : {
      "versionColumnName" : "VERSION",
      "lockingStrategy" : "NONE",
      "overrideStrategy" : "INHERIT"
    },
    "temporals" : [ ],
    "type" : "TABLE"
  }, {
    "catalog" : "StudentPortal_DB",
    "columns" : [ {
      "columnValue" : {
        "insertable" : true,
        "updatable" : true,
        "defaultValue" : null,
        "type" : "user-defined"
      },
      "constraintList" : null,
      "fieldName" : "academicYear",
      "foreignKey" : false,
      "generatorType" : "assigned",
      "generatorValue" : null,
      "hidden" : false,
      "javaType" : "date",
      "length" : 0,
      "name" : "ACADEMIC_YEAR",
      "nullable" : false,
      "oldName" : "ACADEMIC_YEAR",
      "partOfAnyRelation" : false,
      "partOfForeignKey" : false,
      "partOfPrimaryKey" : true,
      "partOfUniqueKey" : false,
      "period" : false,
      "precision" : 0,
      "primaryKey" : false,
      "scale" : 0,
      "sequenceSchema" : null,
      "sqlType" : "date",
      "unique" : false
    }, {
      "columnValue" : {
        "insertable" : true,
        "updatable" : true,
        "defaultValue" : null,
        "type" : "user-defined"
      },
      "constraintList" : null,
      "fieldName" : "rollnumber",
      "foreignKey" : false,
      "generatorType" : "assigned",
      "generatorValue" : null,
      "hidden" : false,
      "javaType" : "integer",
      "length" : 0,
      "name" : "ROLLNUMBER",
      "nullable" : false,
      "oldName" : "ROLLNUMBER",
      "partOfAnyRelation" : false,
      "partOfForeignKey" : false,
      "partOfPrimaryKey" : true,
      "partOfUniqueKey" : false,
      "period" : false,
      "precision" : 10,
      "primaryKey" : false,
      "scale" : 0,
      "sequenceSchema" : null,
      "sqlType" : "number",
      "unique" : false
    }, {
      "columnValue" : {
        "insertable" : true,
        "updatable" : true,
        "defaultValue" : null,
        "type" : "user-defined"
      },
      "constraintList" : null,
      "fieldName" : "standard",
      "foreignKey" : false,
      "generatorType" : "assigned",
      "generatorValue" : null,
      "hidden" : false,
      "javaType" : "string",
      "length" : 255,
      "name" : "STANDARD",
      "nullable" : false,
      "oldName" : "STANDARD",
      "partOfAnyRelation" : false,
      "partOfForeignKey" : false,
      "partOfPrimaryKey" : true,
      "partOfUniqueKey" : false,
      "period" : false,
      "precision" : 0,
      "primaryKey" : false,
      "scale" : 0,
      "sequenceSchema" : null,
      "sqlType" : "string",
      "unique" : false
    }, {
      "columnValue" : {
        "insertable" : true,
        "updatable" : true,
        "defaultValue" : null,
        "type" : "user-defined"
      },
      "constraintList" : null,
      "fieldName" : "studentId",
      "foreignKey" : false,
      "generatorType" : "assigned",
      "generatorValue" : null,
      "hidden" : false,
      "javaType" : "integer",
      "length" : 0,
      "name" : "STUDENT_ID",
      "nullable" : false,
      "oldName" : "STUDENT_ID",
      "partOfAnyRelation" : false,
      "partOfForeignKey" : false,
      "partOfPrimaryKey" : true,
      "partOfUniqueKey" : false,
      "period" : false,
      "precision" : 10,
      "primaryKey" : false,
      "scale" : 0,
      "sequenceSchema" : null,
      "sqlType" : "number",
      "unique" : false
    } ],
    "constraints" : [ ],
    "entityName" : "StudentAcademics",
    "filter" : null,
    "fullyQualifiedName" : "com.student_usecase.studentportal_db.StudentAcademics",
    "ignoreRefreshAfterInsert" : false,
    "name" : "STUDENT_ACADEMICS",
    "oldName" : "STUDENT_ACADEMICS",
    "primaryKey" : {
      "columns" : [ "ACADEMIC_YEAR", "ROLLNUMBER", "STANDARD", "STUDENT_ID" ],
      "composite" : true,
      "generator" : {
        "generatorType" : "assigned",
        "generatorValue" : null,
        "schemaName" : null
      },
      "name" : "PRIMARY",
      "virtual" : false
    },
    "relations" : [ ],
    "schema" : null,
    "tableDataLockingOptions" : {
      "versionColumnName" : "VERSION",
      "lockingStrategy" : "NONE",
      "overrideStrategy" : "INHERIT"
    },
    "temporals" : [ ],
    "type" : "TABLE"
  }, {
    "catalog" : "StudentPortal_DB",
    "columns" : [ {
      "columnValue" : {
        "insertable" : true,
        "updatable" : true,
        "defaultValue" : null,
        "type" : "user-defined"
      },
      "constraintList" : null,
      "fieldName" : "address",
      "foreignKey" : false,
      "generatorType" : "assigned",
      "generatorValue" : null,
      "hidden" : false,
      "javaType" : "string",
      "length" : 255,
      "name" : "ADDRESS",
      "nullable" : false,
      "oldName" : "ADDRESS",
      "partOfAnyRelation" : false,
      "partOfForeignKey" : false,
      "partOfPrimaryKey" : true,
      "partOfUniqueKey" : false,
      "period" : false,
      "precision" : 0,
      "primaryKey" : false,
      "scale" : 0,
      "sequenceSchema" : null,
      "sqlType" : "string",
      "unique" : false
    }, {
      "columnValue" : {
        "insertable" : true,
        "updatable" : true,
        "defaultValue" : null,
        "type" : "user-defined"
      },
      "constraintList" : null,
      "fieldName" : "contactNumber",
      "foreignKey" : false,
      "generatorType" : "assigned",
      "generatorValue" : null,
      "hidden" : false,
      "javaType" : "big_integer",
      "length" : 0,
      "name" : "CONTACT_NUMBER",
      "nullable" : false,
      "oldName" : "CONTACT_NUMBER",
      "partOfAnyRelation" : false,
      "partOfForeignKey" : false,
      "partOfPrimaryKey" : true,
      "partOfUniqueKey" : false,
      "period" : false,
      "precision" : 20,
      "primaryKey" : false,
      "scale" : 0,
      "sequenceSchema" : null,
      "sqlType" : "number",
      "unique" : false
    }, {
      "columnValue" : {
        "insertable" : true,
        "updatable" : true,
        "defaultValue" : null,
        "type" : "user-defined"
      },
      "constraintList" : null,
      "fieldName" : "dateofbirth",
      "foreignKey" : false,
      "generatorType" : "assigned",
      "generatorValue" : null,
      "hidden" : false,
      "javaType" : "date",
      "length" : 0,
      "name" : "DATEOFBIRTH",
      "nullable" : false,
      "oldName" : "DATEOFBIRTH",
      "partOfAnyRelation" : false,
      "partOfForeignKey" : false,
      "partOfPrimaryKey" : true,
      "partOfUniqueKey" : false,
      "period" : false,
      "precision" : 0,
      "primaryKey" : false,
      "scale" : 0,
      "sequenceSchema" : null,
      "sqlType" : "date",
      "unique" : false
    }, {
      "columnValue" : {
        "insertable" : true,
        "updatable" : true,
        "defaultValue" : null,
        "type" : "user-defined"
      },
      "constraintList" : null,
      "fieldName" : "fatherName",
      "foreignKey" : false,
      "generatorType" : "assigned",
      "generatorValue" : null,
      "hidden" : false,
      "javaType" : "string",
      "length" : 255,
      "name" : "FATHER_NAME",
      "nullable" : false,
      "oldName" : "FATHER_NAME",
      "partOfAnyRelation" : false,
      "partOfForeignKey" : false,
      "partOfPrimaryKey" : true,
      "partOfUniqueKey" : false,
      "period" : false,
      "precision" : 0,
      "primaryKey" : false,
      "scale" : 0,
      "sequenceSchema" : null,
      "sqlType" : "string",
      "unique" : false
    }, {
      "columnValue" : {
        "insertable" : true,
        "updatable" : true,
        "defaultValue" : null,
        "type" : "user-defined"
      },
      "constraintList" : null,
      "fieldName" : "joiningDate",
      "foreignKey" : false,
      "generatorType" : "assigned",
      "generatorValue" : null,
      "hidden" : false,
      "javaType" : "date",
      "length" : 0,
      "name" : "JOINING_DATE",
      "nullable" : false,
      "oldName" : "JOINING_DATE",
      "partOfAnyRelation" : false,
      "partOfForeignKey" : false,
      "partOfPrimaryKey" : true,
      "partOfUniqueKey" : false,
      "period" : false,
      "precision" : 0,
      "primaryKey" : false,
      "scale" : 0,
      "sequenceSchema" : null,
      "sqlType" : "date",
      "unique" : false
    }, {
      "columnValue" : {
        "insertable" : true,
        "updatable" : true,
        "defaultValue" : null,
        "type" : "user-defined"
      },
      "constraintList" : null,
      "fieldName" : "studentId",
      "foreignKey" : false,
      "generatorType" : "assigned",
      "generatorValue" : null,
      "hidden" : false,
      "javaType" : "integer",
      "length" : 0,
      "name" : "STUDENT_ID",
      "nullable" : false,
      "oldName" : "STUDENT_ID",
      "partOfAnyRelation" : false,
      "partOfForeignKey" : false,
      "partOfPrimaryKey" : true,
      "partOfUniqueKey" : false,
      "period" : false,
      "precision" : 10,
      "primaryKey" : false,
      "scale" : 0,
      "sequenceSchema" : null,
      "sqlType" : "number",
      "unique" : false
    }, {
      "columnValue" : {
        "insertable" : true,
        "updatable" : true,
        "defaultValue" : null,
        "type" : "user-defined"
      },
      "constraintList" : null,
      "fieldName" : "studentName",
      "foreignKey" : false,
      "generatorType" : "assigned",
      "generatorValue" : null,
      "hidden" : false,
      "javaType" : "string",
      "length" : 255,
      "name" : "STUDENT_NAME",
      "nullable" : false,
      "oldName" : "STUDENT_NAME",
      "partOfAnyRelation" : false,
      "partOfForeignKey" : false,
      "partOfPrimaryKey" : true,
      "partOfUniqueKey" : false,
      "period" : false,
      "precision" : 0,
      "primaryKey" : false,
      "scale" : 0,
      "sequenceSchema" : null,
      "sqlType" : "string",
      "unique" : false
    } ],
    "constraints" : [ ],
    "entityName" : "StudentDetails",
    "filter" : null,
    "fullyQualifiedName" : "com.student_usecase.studentportal_db.StudentDetails",
    "ignoreRefreshAfterInsert" : false,
    "name" : "STUDENT_DETAILS",
    "oldName" : "STUDENT_DETAILS",
    "primaryKey" : {
      "columns" : [ "ADDRESS", "CONTACT_NUMBER", "DATEOFBIRTH", "FATHER_NAME", "JOINING_DATE", "STUDENT_ID", "STUDENT_NAME" ],
      "composite" : true,
      "generator" : {
        "generatorType" : "assigned",
        "generatorValue" : null,
        "schemaName" : null
      },
      "name" : "PRIMARY",
      "virtual" : false
    },
    "relations" : [ ],
    "schema" : null,
    "tableDataLockingOptions" : {
      "versionColumnName" : "VERSION",
      "lockingStrategy" : "NONE",
      "overrideStrategy" : "INHERIT"
    },
    "temporals" : [ ],
    "type" : "TABLE"
  }, {
    "catalog" : "StudentPortal_DB",
    "columns" : [ {
      "columnValue" : {
        "insertable" : true,
        "updatable" : true,
        "defaultValue" : null,
        "type" : "user-defined"
      },
      "constraintList" : null,
      "fieldName" : "testId",
      "foreignKey" : false,
      "generatorType" : "assigned",
      "generatorValue" : null,
      "hidden" : false,
      "javaType" : "integer",
      "length" : 0,
      "name" : "TEST_ID",
      "nullable" : false,
      "oldName" : "TEST_ID",
      "partOfAnyRelation" : false,
      "partOfForeignKey" : false,
      "partOfPrimaryKey" : true,
      "partOfUniqueKey" : false,
      "period" : false,
      "precision" : 10,
      "primaryKey" : false,
      "scale" : 0,
      "sequenceSchema" : null,
      "sqlType" : "number",
      "unique" : false
    }, {
      "columnValue" : {
        "insertable" : true,
        "updatable" : true,
        "defaultValue" : null,
        "type" : "user-defined"
      },
      "constraintList" : null,
      "fieldName" : "testName",
      "foreignKey" : false,
      "generatorType" : "assigned",
      "generatorValue" : null,
      "hidden" : false,
      "javaType" : "string",
      "length" : 255,
      "name" : "TEST_NAME",
      "nullable" : false,
      "oldName" : "TEST_NAME",
      "partOfAnyRelation" : false,
      "partOfForeignKey" : false,
      "partOfPrimaryKey" : true,
      "partOfUniqueKey" : false,
      "period" : false,
      "precision" : 0,
      "primaryKey" : false,
      "scale" : 0,
      "sequenceSchema" : null,
      "sqlType" : "string",
      "unique" : false
    } ],
    "constraints" : [ ],
    "entityName" : "TestDetails",
    "filter" : null,
    "fullyQualifiedName" : "com.student_usecase.studentportal_db.TestDetails",
    "ignoreRefreshAfterInsert" : false,
    "name" : "TEST_DETAILS",
    "oldName" : "TEST_DETAILS",
    "primaryKey" : {
      "columns" : [ "TEST_ID", "TEST_NAME" ],
      "composite" : true,
      "generator" : {
        "generatorType" : "assigned",
        "generatorValue" : null,
        "schemaName" : null
      },
      "name" : "PRIMARY",
      "virtual" : false
    },
    "relations" : [ ],
    "schema" : null,
    "tableDataLockingOptions" : {
      "versionColumnName" : "VERSION",
      "lockingStrategy" : "NONE",
      "overrideStrategy" : "INHERIT"
    },
    "temporals" : [ ],
    "type" : "TABLE"
  }, {
    "catalog" : "StudentPortal_DB",
    "columns" : [ {
      "columnValue" : {
        "insertable" : true,
        "updatable" : true,
        "defaultValue" : null,
        "type" : "user-defined"
      },
      "constraintList" : null,
      "fieldName" : "userId",
      "foreignKey" : false,
      "generatorType" : "assigned",
      "generatorValue" : null,
      "hidden" : false,
      "javaType" : "integer",
      "length" : 0,
      "name" : "USER_ID",
      "nullable" : false,
      "oldName" : "USER_ID",
      "partOfAnyRelation" : false,
      "partOfForeignKey" : false,
      "partOfPrimaryKey" : true,
      "partOfUniqueKey" : true,
      "period" : false,
      "precision" : 10,
      "primaryKey" : true,
      "scale" : 0,
      "sequenceSchema" : null,
      "sqlType" : "number",
      "unique" : true
    }, {
      "columnValue" : {
        "insertable" : true,
        "updatable" : true,
        "defaultValue" : null,
        "type" : "user-defined"
      },
      "constraintList" : null,
      "fieldName" : "password",
      "foreignKey" : false,
      "generatorType" : "assigned",
      "generatorValue" : null,
      "hidden" : false,
      "javaType" : "string",
      "length" : 255,
      "name" : "PASSWORD",
      "nullable" : true,
      "oldName" : "PASSWORD",
      "partOfAnyRelation" : false,
      "partOfForeignKey" : false,
      "partOfPrimaryKey" : false,
      "partOfUniqueKey" : false,
      "period" : false,
      "precision" : 0,
      "primaryKey" : false,
      "scale" : 0,
      "sequenceSchema" : null,
      "sqlType" : "string",
      "unique" : false
    }, {
      "columnValue" : {
        "insertable" : true,
        "updatable" : true,
        "defaultValue" : null,
        "type" : "user-defined"
      },
      "constraintList" : null,
      "fieldName" : "role",
      "foreignKey" : false,
      "generatorType" : "assigned",
      "generatorValue" : null,
      "hidden" : false,
      "javaType" : "string",
      "length" : 255,
      "name" : "ROLE",
      "nullable" : true,
      "oldName" : "ROLE",
      "partOfAnyRelation" : false,
      "partOfForeignKey" : false,
      "partOfPrimaryKey" : false,
      "partOfUniqueKey" : false,
      "period" : false,
      "precision" : 0,
      "primaryKey" : false,
      "scale" : 0,
      "sequenceSchema" : null,
      "sqlType" : "string",
      "unique" : false
    }, {
      "columnValue" : {
        "insertable" : true,
        "updatable" : true,
        "defaultValue" : null,
        "type" : "user-defined"
      },
      "constraintList" : null,
      "fieldName" : "userName",
      "foreignKey" : false,
      "generatorType" : "assigned",
      "generatorValue" : null,
      "hidden" : false,
      "javaType" : "string",
      "length" : 255,
      "name" : "USER_NAME",
      "nullable" : true,
      "oldName" : "USER_NAME",
      "partOfAnyRelation" : false,
      "partOfForeignKey" : false,
      "partOfPrimaryKey" : false,
      "partOfUniqueKey" : false,
      "period" : false,
      "precision" : 0,
      "primaryKey" : false,
      "scale" : 0,
      "sequenceSchema" : null,
      "sqlType" : "string",
      "unique" : false
    } ],
    "constraints" : [ ],
    "entityName" : "UserLogin",
    "filter" : null,
    "fullyQualifiedName" : "com.student_usecase.studentportal_db.UserLogin",
    "ignoreRefreshAfterInsert" : false,
    "name" : "USER_LOGIN",
    "oldName" : "USER_LOGIN",
    "primaryKey" : {
      "columns" : [ "USER_ID" ],
      "composite" : false,
      "generator" : {
        "generatorType" : "assigned",
        "generatorValue" : null,
        "schemaName" : null
      },
      "name" : "PRIMARY",
      "virtual" : false
    },
    "relations" : [ ],
    "schema" : null,
    "tableDataLockingOptions" : {
      "versionColumnName" : "VERSION",
      "lockingStrategy" : "NONE",
      "overrideStrategy" : "INHERIT"
    },
    "temporals" : [ ],
    "type" : "TABLE"
  } ]
}